finrl/__init__.py
finrl/__main__.py
finrl/config.py
finrl/config_private.py
finrl/config_tickers.py
finrl/main.py
finrl/plot.py
finrl/test.py
finrl/trade.py
finrl/train.py
finrl/agents/__init__.py
finrl/agents/elegantrl/__init__.py
finrl/agents/elegantrl/models.py
finrl/agents/portfolio_optimization/__init__.py
finrl/agents/portfolio_optimization/algorithms.py
finrl/agents/portfolio_optimization/architectures.py
finrl/agents/portfolio_optimization/models.py
finrl/agents/portfolio_optimization/utils.py
finrl/agents/rllib/__init__.py
finrl/agents/rllib/drllibv2.py
finrl/agents/rllib/models.py
finrl/agents/stablebaselines3/__init__.py
finrl/agents/stablebaselines3/hyperparams_opt.py
finrl/agents/stablebaselines3/models.py
finrl/agents/stablebaselines3/tune_sb3.py
finrl/applications/__init__.py
finrl/applications/cryptocurrency_trading/__init__.py
finrl/applications/high_frequency_trading/__init__.py
finrl/applications/portfolio_allocation/__init__.py
finrl/applications/stock_trading/__init__.py
finrl/applications/stock_trading/ensemble_stock_trading.py
finrl/applications/stock_trading/fundamental_stock_trading.py
finrl/applications/stock_trading/stock_trading.py
finrl/applications/stock_trading/stock_trading_rolling_window.py
finrl/meta/__init__.py
finrl/meta/data_processor.py
finrl/meta/meta_config.py
finrl/meta/data_processors/__init__.py
finrl/meta/data_processors/func.py
finrl/meta/data_processors/processor_alpaca.py
finrl/meta/data_processors/processor_ccxt.py
finrl/meta/data_processors/processor_joinquant.py
finrl/meta/data_processors/processor_quantconnect.py
finrl/meta/data_processors/processor_wrds.py
finrl/meta/data_processors/processor_yahoofinance.py
finrl/meta/env_cryptocurrency_trading/__init__.py
finrl/meta/env_cryptocurrency_trading/env_btc_ccxt.py
finrl/meta/env_cryptocurrency_trading/env_multiple_crypto.py
finrl/meta/env_portfolio_allocation/__init__.py
finrl/meta/env_portfolio_allocation/env_portfolio.py
FinRL-0.3.7.dist-info/LICENSE
FinRL-0.3.7.dist-info/METADATA
FinRL-0.3.7.dist-info/WHEEL
FinRL-0.3.7.dist-info/top_level.txt
FinRL-0.3.7.dist-info/RECORD
