Metadata-Version: 2.1
Name: FinRL
Version: 0.3.7
Summary: FinRL: Financial Reinforcement Learning Framework.
Home-page: https://github.com/AI4Finance-Foundation/FinRL
Author: AI4Finance Foundation
Author-email: contact@ai4finance.org
License: MIT
Keywords: Reinforcement Learning,Finance
Classifier: License :: OSI Approved :: MIT License
Classifier: Programming Language :: Python
Classifier: Programming Language :: Python :: 3
Classifier: Programming Language :: Python :: 3.7
Classifier: Programming Language :: Python :: 3.8
Classifier: Programming Language :: Python :: 3.9
Classifier: Programming Language :: Python :: 3.10
Classifier: Programming Language :: Python :: Implementation :: CPython
Classifier: Programming Language :: Python :: Implementation :: PyPy
Requires-Python: >=3.7
License-File: LICENSE
